LICENSE.md
MANIFEST.in
README.md
setup.cfg
setup.py
frodocs_plugin1/__init__.py
frodocs_plugin1/arrange.py
frodocs_plugin1/meta.py
frodocs_plugin1/navigation.py
frodocs_plugin1/options.py
frodocs_plugin1/plugin.py
frodocs_plugin1/utils.py
frodocs_plugin1.egg-info/PKG-INFO
frodocs_plugin1.egg-info/SOURCES.txt
frodocs_plugin1.egg-info/dependency_links.txt
frodocs_plugin1.egg-info/entry_points.txt
frodocs_plugin1.egg-info/requires.txt
frodocs_plugin1.egg-info/top_level.txt