Metadata-Version: 1.2
Name: frodocs-plugin1
Version: 1.0.2
Summary: Test a plugin
Home-page: https://frodo.ga
Author: Ham
Author-email: lwonderlich@gmail.com
License: MIT
Keywords: frodocs python markdown wiki
Platform: UNKNOWN
Classifier: Development Status :: 5 - Production/Stable
Classifier: Intended Audience :: Developers
Classifier: Intended Audience :: Information Technology
Classifier: License :: OSI Approved :: MIT License
Classifier: Programming Language :: Python
Classifier: Programming Language :: Python :: 3 :: Only
Classifier: Programming Language :: Python :: 3.5
Classifier: Programming Language :: Python :: 3.6
Classifier: Programming Language :: Python :: 3.7
Requires-Python: >=3.5
